parfive/__init__.py
parfive/_version.py
parfive/config.py
parfive/conftest.py
parfive/downloader.py
parfive/main.py
parfive/results.py
parfive/utils.py
parfive/tests/__init__.py
parfive/tests/localserver.py
parfive/tests/test_aiofiles.py
parfive/tests/test_config.py
parfive/tests/test_downloader.py
parfive/tests/test_downloader_multipart.py
parfive/tests/test_main.py
parfive/tests/test_utils.py
parfive-2.1.0.dist-info/LICENSE
parfive-2.1.0.dist-info/METADATA
parfive-2.1.0.dist-info/WHEEL
parfive-2.1.0.dist-info/entry_points.txt
parfive-2.1.0.dist-info/top_level.txt
parfive-2.1.0.dist-info/RECORD
