Metadata-Version: 2.1
Name: parfive
Version: 2.1.0
Summary: A HTTP and FTP parallel file downloader.
Home-page: https://parfive.readthedocs.io/
Author: "Stuart Mumford"
Author-email: "stuart@cadair.com"
License: MIT
Classifier: Programming Language :: Python :: 3
Classifier: Programming Language :: Python :: 3.8
Classifier: Programming Language :: Python :: 3.9
Classifier: Programming Language :: Python :: 3.10
Classifier: Programming Language :: Python :: 3.11
Classifier: Programming Language :: Python :: 3.12
Requires-Python: >=3.8
License-File: LICENSE
Requires-Dist: tqdm>=4.27.0
Requires-Dist: aiohttp
Provides-Extra: ftp
Requires-Dist: aioftp>=0.17.1; extra == "ftp"
Provides-Extra: tests
Requires-Dist: pytest; extra == "tests"
Requires-Dist: pytest-localserver; extra == "tests"
Requires-Dist: pytest-asyncio; extra == "tests"
Requires-Dist: pytest-socket; extra == "tests"
Requires-Dist: pytest-cov; extra == "tests"
Requires-Dist: aiofiles; extra == "tests"
Provides-Extra: docs
Requires-Dist: sphinx; extra == "docs"
Requires-Dist: sphinx-automodapi; extra == "docs"
Requires-Dist: sphinx-autodoc-typehints; extra == "docs"
Requires-Dist: sphinx-contributors; extra == "docs"
Requires-Dist: sphinx-book-theme; extra == "docs"
